hellocivis/__init__.py
hellocivis/api.py
hellocivis/hello_civis.py
hellocivis/scripts/run_script.py
hellocivis-1.0.5.dist-info/DESCRIPTION.rst
hellocivis-1.0.5.dist-info/METADATA
hellocivis-1.0.5.dist-info/RECORD
hellocivis-1.0.5.dist-info/WHEEL
hellocivis-1.0.5.dist-info/entry_points.txt
hellocivis-1.0.5.dist-info/metadata.json
hellocivis-1.0.5.dist-info/top_level.txt
